borg_qt/__init__.py
borg_qt/__main__.py
borg_qt/borg_interface.py
borg_qt/config.py
borg_qt/help.py
borg_qt/helper.py
borg_qt/main_window.py
borg_qt/progress.py
borg_qt/systemd.py
borg_qt/static/UI/ArchiveDetails.ui
borg_qt/static/UI/Help.ui
borg_qt/static/UI/MainWindow.ui
borg_qt/static/UI/Progress.ui
borg_qt/static/UI/Settings.ui
borg_qt/static/UI/main_window.png
borg_qt/static/icons/alert-circle.svg
borg_qt/static/icons/delete.svg
borg_qt/static/icons/hard-drive.svg
borg_qt/static/icons/help-circle.svg
borg_qt/static/icons/info.svg
borg_qt/static/icons/minus.svg
borg_qt/static/icons/plus.svg
borg_qt/static/icons/rotate-ccw.svg
borg_qt/static/icons/save.svg
borg_qt/static/icons/settings.svg
borg_qt-2019.5.30.1.dist-info/LICENSE
borg_qt-2019.5.30.1.dist-info/METADATA
borg_qt-2019.5.30.1.dist-info/WHEEL
borg_qt-2019.5.30.1.dist-info/entry_points.txt
borg_qt-2019.5.30.1.dist-info/top_level.txt
borg_qt-2019.5.30.1.dist-info/RECORD
