Metadata-Version: 2.1
Name: borg-qt
Version: 2019.5.30.1
Summary: A graphical frontend for BorgBackup.
Home-page: https://github.com/borg-qt/borg-qt.git
Author: Andreas Zweili
Author-email: 
License: GPLv3
Platform: UNKNOWN
Classifier: License :: OSI Approved :: GNU General Public License v3 or later (GPLv3+)
Classifier: Programming Language :: Python
Classifier: Programming Language :: Python :: 3
Classifier: Programming Language :: Python :: 3.6
Classifier: Programming Language :: Python :: Implementation :: CPython
Classifier: Programming Language :: Python :: Implementation :: PyPy
Requires-Python: >=3.6.0
Requires-Dist: PyQt5
